Metadata-Version: 2.1
Name: yolo-extension
Version: 0.3.20
Summary: Manage AWS infrastructure and microservices across multiple stages/accounts
Home-page: 
Maintainer: Akshaya PS
Maintainer-email: akshaya.ps@rackspace.com
Classifier: Development Status :: 3 - Alpha
Classifier: License :: OSI Approved :: Apache Software License
Classifier: Intended Audience :: Developers
Classifier: Intended Audience :: Information Technology
Classifier: Operating System :: OS Independent
Classifier: Programming Language :: Python :: 2.7
Classifier: Programming Language :: Python :: 3.6
Classifier: Programming Language :: Python :: 3.10
Classifier: Topic :: Software Development :: Build Tools
License-File: LICENSE
Requires-Dist: awscli
Requires-Dist: boto3
Requires-Dist: botocore >=1.7.18
Requires-Dist: click
Requires-Dist: docker ==3.4.0
Requires-Dist: jinja2
Requires-Dist: keyring ==15.0.0
Requires-Dist: keyrings.alt
Requires-Dist: requests
Requires-Dist: ruamel.yaml ==0.17.21
Requires-Dist: tabulate
Requires-Dist: voluptuous
